{
  "num_vehicles": 4,
  "vehicle_capacities": [80000, 80000, 60000, 60000],
  "warehouse_address": "Keßlerstraße 12 Jena",
  "customers": {
    "addresses": [
      "Ernst-Schneller-Straße 14 Jena",
      "Klosterweg 6B Jena",
      "Ernst-Zielinski-Straße 13 Jena",
      "Leutragraben 2 Jena",
      "Spitzweidenweg 35 Jena",
      "Hegelstraße 1 Jena",
      "Sachseneckweg 20 Jena",
      "Beethovenstraße 15 Jena",
      "Judith-Auer-Straße 13 Jena",
      "Carolinenstraße 48 Jena",
      "Musäusring 32 Jena",
      "Rudolf-Breitscheid-Straße 51 Jena",
      "Salvador-Allende-Platz 17 Jena",
      "Platanenstraße 6 Jena",
      "Werner-Seelenbinder-Straße 15 Jena",
      "Fritz-Ritter-Straße 29 Jena",
      "Emil-Wölk-Straße 3 Jena",
      "Hans-Berger-Straße 10 Jena",
      "Georg-Schumann-Weg 20 Jena",
      "Olga-Benario-Weg 7 Jena",
      "Susanne-Bohl-Straße 4 Jena",
      "Hinterweg 9 Jena",
      "Am Jagdberg 11 Jena",
      "Frongasse 5 Jena",
      "Rudolstädter Straße 47 Jena",
      "Geraer Straße 54 Jena",
      "Anna-Siemsen-Straße 60 Jena",
      "Distelweg 14 Jena",
      "Lilienweg 1 Jena",
      "Mühlenstraße 33 Jena",
      "Jansonstraße 10 Jena",
      "Schroeterstraße 5 Jena",
      "Talstraße 56 Jena",
      "Schaefferstraße 15 Jena",
      "Paraschkenmühle 16 Jena",
      "Schillbachstraße 4 Jena",
      "Arvid-Harnack-Straße 24 Jena",
      "Friesweg 10 Jena",
      "Nollendorfer Straße 16 Jena"
    ],
    "demands": [
      0,
      15000,
      7000,
      5000,
      2000,
      5000,
      7000,
      1000,
      4000,
      7000,
      4000,
      13000,
      1000,
      7000,
      5000,
      2000,
      4000,
      6000,
      13000,
      5000,
      1000,
      3000,
      8000,
      4000,
      8000,
      5000,
      13000,
      5000,
      1000,
      3000,
      9000,
      6000,
      3000,
      6000,
      10000,
      8000,
      4000,
      2000,
      8000,
      7000
    ]
  }
}